{
	"name": "Coin",
	"plugin-id": "Sprite",
	"sid": 185169360796796,
	"isGlobal": false,
	"instanceVariables": [],
	"behaviorTypes": [
		{
			"behaviorId": "Persist",
			"name": "Persist",
			"sid": 948941824090263
		}
	],
	"effectTypes": [],
	"animations": {
		"items": [
			{
				"frames": [
					{
						"width": 16,
						"height": 16,
						"originX": 0.5,
						"originY": 0.5,
						"originalSource": "",
						"exportFormat": "lossless",
						"exportQuality": 0.8,
						"imageSpriteId": 3193017,
						"collisionPoly": {
							"points": [
								0.625,
								0.8125,
								0.375,
								0.8125,
								0.1875,
								0.625,
								0.1875,
								0.375,
								0.375,
								0.1875,
								0.625,
								0.1875,
								0.8125,
								0.375,
								0.8125,
								0.625
							]
						},
						"useCollisionPoly": true,
						"duration": 1,
						"tag": ""
					},
					{
						"width": 16,
						"height": 16,
						"originX": 0.5,
						"originY": 0.5,
						"originalSource": "",
						"exportFormat": "lossless",
						"exportQuality": 0.8,
						"imageSpriteId": 4130854,
						"collisionPoly": {
							"points": [
								0.4375,
								0.1875,
								0.5625,
								0.1875,
								0.75,
								0.375,
								0.75,
								0.625,
								0.5625,
								0.8125,
								0.4375,
								0.8125,
								0.25,
								0.625,
								0.25,
								0.375
							]
						},
						"useCollisionPoly": true,
						"duration": 1,
						"tag": ""
					},
					{
						"width": 16,
						"height": 16,
						"originX": 0.5,
						"originY": 0.5,
						"originalSource": "",
						"exportFormat": "lossless",
						"exportQuality": 0.8,
						"imageSpriteId": 2797811,
						"collisionPoly": {
							"points": [
								0.4375,
								0.1875,
								0.5625,
								0.1875,
								0.625,
								0.25,
								0.625,
								0.75,
								0.5625,
								0.8125,
								0.4375,
								0.8125,
								0.375,
								0.75,
								0.375,
								0.25
							]
						},
						"useCollisionPoly": true,
						"duration": 1,
						"tag": ""
					},
					{
						"width": 16,
						"height": 16,
						"originX": 0.5,
						"originY": 0.5,
						"originalSource": "",
						"exportFormat": "lossless",
						"exportQuality": 0.8,
						"imageSpriteId": 4897870,
						"collisionPoly": {
							"points": [
								0.4375,
								0.1875,
								0.5625,
								0.1875,
								0.75,
								0.375,
								0.75,
								0.625,
								0.5625,
								0.8125,
								0.4375,
								0.8125,
								0.25,
								0.625,
								0.25,
								0.375
							]
						},
						"useCollisionPoly": true,
						"duration": 1,
						"tag": ""
					}
				],
				"sid": 335321714619091,
				"name": "Animation 1",
				"isLooping": true,
				"isPingPong": false,
				"repeatCount": 1,
				"repeatTo": 0,
				"speed": 5
			}
		],
		"subfolders": []
	}
}