{
	"name": "Sprite2",
	"plugin-id": "Sprite",
	"sid": 785416791865424,
	"isGlobal": false,
	"instanceVariables": [],
	"behaviorTypes": [],
	"effectTypes": [],
	"animations": {
		"items": [
			{
				"frames": [
					{
						"width": 245,
						"height": 345,
						"originX": 0.5,
						"originY": 0.5,
						"originalSource": "",
						"exportFormat": "lossless",
						"exportQuality": 0.8,
						"imageSpriteId": 5813515,
						"useCollisionPoly": true,
						"duration": 1,
						"tag": ""
					},
					{
						"width": 245,
						"height": 345,
						"originX": 0.5,
						"originY": 0.5,
						"originalSource": "",
						"exportFormat": "lossless",
						"exportQuality": 0.8,
						"imageSpriteId": 540483,
						"useCollisionPoly": true,
						"duration": 1,
						"tag": ""
					},
					{
						"width": 245,
						"height": 345,
						"originX": 0.5,
						"originY": 0.5,
						"originalSource": "",
						"exportFormat": "lossless",
						"exportQuality": 0.8,
						"imageSpriteId": 3431070,
						"useCollisionPoly": true,
						"duration": 1,
						"tag": ""
					},
					{
						"width": 245,
						"height": 345,
						"originX": 0.5,
						"originY": 0.5,
						"originalSource": "",
						"exportFormat": "lossless",
						"exportQuality": 0.8,
						"imageSpriteId": 4988078,
						"useCollisionPoly": true,
						"duration": 1,
						"tag": ""
					},
					{
						"width": 245,
						"height": 345,
						"originX": 0.5,
						"originY": 0.5,
						"originalSource": "",
						"exportFormat": "lossless",
						"exportQuality": 0.8,
						"imageSpriteId": 8935456,
						"useCollisionPoly": true,
						"duration": 1,
						"tag": ""
					},
					{
						"width": 245,
						"height": 345,
						"originX": 0.5,
						"originY": 0.5,
						"originalSource": "",
						"exportFormat": "lossless",
						"exportQuality": 0.8,
						"imageSpriteId": 1032668,
						"useCollisionPoly": true,
						"duration": 1,
						"tag": ""
					},
					{
						"width": 245,
						"height": 345,
						"originX": 0.5,
						"originY": 0.5,
						"originalSource": "",
						"exportFormat": "lossless",
						"exportQuality": 0.8,
						"imageSpriteId": 7154954,
						"useCollisionPoly": true,
						"duration": 1,
						"tag": ""
					},
					{
						"width": 245,
						"height": 345,
						"originX": 0.5,
						"originY": 0.5,
						"originalSource": "",
						"exportFormat": "lossless",
						"exportQuality": 0.8,
						"imageSpriteId": 6081606,
						"useCollisionPoly": true,
						"duration": 1,
						"tag": ""
					},
					{
						"width": 245,
						"height": 345,
						"originX": 0.5,
						"originY": 0.5,
						"originalSource": "",
						"exportFormat": "lossless",
						"exportQuality": 0.8,
						"imageSpriteId": 3359953,
						"useCollisionPoly": true,
						"duration": 1,
						"tag": ""
					},
					{
						"width": 245,
						"height": 345,
						"originX": 0.5,
						"originY": 0.5,
						"originalSource": "",
						"exportFormat": "lossless",
						"exportQuality": 0.8,
						"imageSpriteId": 2192839,
						"useCollisionPoly": true,
						"duration": 1,
						"tag": ""
					},
					{
						"width": 245,
						"height": 345,
						"originX": 0.5,
						"originY": 0.5,
						"originalSource": "",
						"exportFormat": "lossless",
						"exportQuality": 0.8,
						"imageSpriteId": 4703262,
						"useCollisionPoly": true,
						"duration": 1,
						"tag": ""
					},
					{
						"width": 245,
						"height": 345,
						"originX": 0.5,
						"originY": 0.5,
						"originalSource": "",
						"exportFormat": "lossless",
						"exportQuality": 0.8,
						"imageSpriteId": 9609753,
						"useCollisionPoly": true,
						"duration": 1,
						"tag": ""
					},
					{
						"width": 245,
						"height": 345,
						"originX": 0.5,
						"originY": 0.5,
						"originalSource": "",
						"exportFormat": "lossless",
						"exportQuality": 0.8,
						"imageSpriteId": 4388140,
						"useCollisionPoly": true,
						"duration": 1,
						"tag": ""
					},
					{
						"width": 245,
						"height": 345,
						"originX": 0.5,
						"originY": 0.5,
						"originalSource": "",
						"exportFormat": "lossless",
						"exportQuality": 0.8,
						"imageSpriteId": 5420339,
						"useCollisionPoly": true,
						"duration": 1,
						"tag": ""
					},
					{
						"width": 245,
						"height": 345,
						"originX": 0.5,
						"originY": 0.5,
						"originalSource": "",
						"exportFormat": "lossless",
						"exportQuality": 0.8,
						"imageSpriteId": 9115642,
						"useCollisionPoly": true,
						"duration": 1,
						"tag": ""
					},
					{
						"width": 245,
						"height": 345,
						"originX": 0.5,
						"originY": 0.5,
						"originalSource": "",
						"exportFormat": "lossless",
						"exportQuality": 0.8,
						"imageSpriteId": 6060609,
						"useCollisionPoly": true,
						"duration": 1,
						"tag": ""
					},
					{
						"width": 245,
						"height": 345,
						"originX": 0.5,
						"originY": 0.5,
						"originalSource": "",
						"exportFormat": "lossless",
						"exportQuality": 0.8,
						"imageSpriteId": 4942321,
						"useCollisionPoly": true,
						"duration": 1,
						"tag": ""
					},
					{
						"width": 245,
						"height": 345,
						"originX": 0.5,
						"originY": 0.5,
						"originalSource": "",
						"exportFormat": "lossless",
						"exportQuality": 0.8,
						"imageSpriteId": 5795321,
						"useCollisionPoly": true,
						"duration": 1,
						"tag": ""
					},
					{
						"width": 245,
						"height": 345,
						"originX": 0.5,
						"originY": 0.5,
						"originalSource": "",
						"exportFormat": "lossless",
						"exportQuality": 0.8,
						"imageSpriteId": 8744831,
						"useCollisionPoly": true,
						"duration": 1,
						"tag": ""
					},
					{
						"width": 245,
						"height": 345,
						"originX": 0.5,
						"originY": 0.5,
						"originalSource": "",
						"exportFormat": "lossless",
						"exportQuality": 0.8,
						"imageSpriteId": 7260317,
						"useCollisionPoly": true,
						"duration": 1,
						"tag": ""
					},
					{
						"width": 245,
						"height": 345,
						"originX": 0.5,
						"originY": 0.5,
						"originalSource": "",
						"exportFormat": "lossless",
						"exportQuality": 0.8,
						"imageSpriteId": 7478244,
						"useCollisionPoly": true,
						"duration": 1,
						"tag": ""
					},
					{
						"width": 245,
						"height": 345,
						"originX": 0.5,
						"originY": 0.5,
						"originalSource": "",
						"exportFormat": "lossless",
						"exportQuality": 0.8,
						"imageSpriteId": 9163481,
						"useCollisionPoly": true,
						"duration": 1,
						"tag": ""
					},
					{
						"width": 245,
						"height": 345,
						"originX": 0.5,
						"originY": 0.5,
						"originalSource": "",
						"exportFormat": "lossless",
						"exportQuality": 0.8,
						"imageSpriteId": 9040729,
						"useCollisionPoly": true,
						"duration": 1,
						"tag": ""
					},
					{
						"width": 245,
						"height": 345,
						"originX": 0.5,
						"originY": 0.5,
						"originalSource": "",
						"exportFormat": "lossless",
						"exportQuality": 0.8,
						"imageSpriteId": 8508462,
						"useCollisionPoly": true,
						"duration": 1,
						"tag": ""
					},
					{
						"width": 245,
						"height": 345,
						"originX": 0.5,
						"originY": 0.5,
						"originalSource": "",
						"exportFormat": "lossless",
						"exportQuality": 0.8,
						"imageSpriteId": 2910900,
						"useCollisionPoly": true,
						"duration": 1,
						"tag": ""
					},
					{
						"width": 245,
						"height": 345,
						"originX": 0.5,
						"originY": 0.5,
						"originalSource": "",
						"exportFormat": "lossless",
						"exportQuality": 0.8,
						"imageSpriteId": 139003,
						"useCollisionPoly": true,
						"duration": 1,
						"tag": ""
					},
					{
						"width": 245,
						"height": 345,
						"originX": 0.5,
						"originY": 0.5,
						"originalSource": "",
						"exportFormat": "lossless",
						"exportQuality": 0.8,
						"imageSpriteId": 2962353,
						"useCollisionPoly": true,
						"duration": 1,
						"tag": ""
					},
					{
						"width": 245,
						"height": 345,
						"originX": 0.5,
						"originY": 0.5,
						"originalSource": "",
						"exportFormat": "lossless",
						"exportQuality": 0.8,
						"imageSpriteId": 3956086,
						"useCollisionPoly": true,
						"duration": 1,
						"tag": ""
					}
				],
				"sid": 509854919563158,
				"name": "Animation 1",
				"isLooping": false,
				"isPingPong": false,
				"repeatCount": 1,
				"repeatTo": 0,
				"speed": 5
			}
		],
		"subfolders": []
	}
}